odoo/addons/delivery_cttexpress/README.rst
odoo/addons/delivery_cttexpress/__init__.py
odoo/addons/delivery_cttexpress/__manifest__.py
odoo/addons/delivery_cttexpress/i18n/delivery_cttexpress.pot
odoo/addons/delivery_cttexpress/i18n/es.po
odoo/addons/delivery_cttexpress/models/__init__.py
odoo/addons/delivery_cttexpress/models/cttexpress_master_data.py
odoo/addons/delivery_cttexpress/models/cttexpress_request.py
odoo/addons/delivery_cttexpress/models/delivery_carrier.py
odoo/addons/delivery_cttexpress/models/stock_picking.py
odoo/addons/delivery_cttexpress/readme/CONFIGURE.rst
odoo/addons/delivery_cttexpress/readme/CONTRIBUTORS.rst
odoo/addons/delivery_cttexpress/readme/CREDITS.rst
odoo/addons/delivery_cttexpress/readme/DESCRIPTION.rst
odoo/addons/delivery_cttexpress/readme/INSTALL.rst
odoo/addons/delivery_cttexpress/readme/ROADMAP.rst
odoo/addons/delivery_cttexpress/readme/USAGE.rst
odoo/addons/delivery_cttexpress/security/ir.model.access.csv
odoo/addons/delivery_cttexpress/static/description/icon.png
odoo/addons/delivery_cttexpress/static/description/icon.svg
odoo/addons/delivery_cttexpress/static/description/index.html
odoo/addons/delivery_cttexpress/tests/__init__.py
odoo/addons/delivery_cttexpress/tests/test_delivery_cttexpress.py
odoo/addons/delivery_cttexpress/views/delivery_cttexpress_view.xml
odoo/addons/delivery_cttexpress/views/stock_picking_views.xml
odoo/addons/delivery_cttexpress/wizards/__init__.py
odoo/addons/delivery_cttexpress/wizards/cttexpress_manifest_wizard.py
odoo/addons/delivery_cttexpress/wizards/cttexpress_manifest_wizard_views.xml
odoo/addons/delivery_cttexpress/wizards/cttexpress_pickup_wizard.py
odoo/addons/delivery_cttexpress/wizards/cttexpress_pickup_wizard.xml
odoo14_addon_delivery_cttexpress-14.0.1.0.1.dist-info/METADATA
odoo14_addon_delivery_cttexpress-14.0.1.0.1.dist-info/WHEEL
odoo14_addon_delivery_cttexpress-14.0.1.0.1.dist-info/top_level.txt
odoo14_addon_delivery_cttexpress-14.0.1.0.1.dist-info/RECORD
